lumopypackage/UserAgent.py
lumopypackage/__init__.py
lumopypackage/downloadBingImg.py
lumopypackage/userPath.py
lumopypackage-0.1.4.dist-info/METADATA
lumopypackage-0.1.4.dist-info/WHEEL
lumopypackage-0.1.4.dist-info/licenses/LICENSE
lumopypackage-0.1.4.dist-info/RECORD
