Metadata-Version: 2.1
Name: LumoPyPackage
Version: 0.1.4
Summary: Lumo's Package
Project-URL: Homepage, https://github.com/RobertLumo/Lumo-s-Package
Project-URL: Bug Tracker, https://github.com/RobertLumo/Lumo-s-Package
Author-email: Lumo <lumo520wm@foxmail.com>
License: Copyright <YEAR> <COPYRIGHT HOLDER>
Classifier: License :: OSI Approved :: MIT License
Classifier: Operating System :: OS Independent
Classifier: Programming Language :: Python :: 3
Requires-Python: >=3.7
